{
 "cmd": "detected_info",
 "param": {
  "target": [
   {
    "signType": 3,
    "signName": "可疑空中目标1",
    "createdTime": "2021-06-22 12:18:44",
    "updateTime": "2021-06-22 12:18:44",
    "lat": 35.6198662,
    "lng": 120.4502664
   },
   {
    "signType": 3,
    "signName": "可疑空中目标2",
    "createdTime": "2021-06-22 12:18:44",
    "updateTime": "2021-06-22 12:18:44",
    "lat": 35.7375217,
    "lng": 120.2689845
   },
   {
    "signType": 2,
    "signName": "可疑水上目标3",
    "createdTime": "2021-06-22 12:18:44",
    "updateTime": "2021-06-22 12:18:44",
    "lat": 35.9286282,
    "lng": 120.2976512
   },
   {
    "signType": 2,
    "signName": "可疑水上目标4",
    "createdTime": "2021-06-22 12:18:44",
    "updateTime": "2021-06-22 12:18:44",
    "lat": 35.9172194,
    "lng": 120.4634717
   }
  ]
 }
}